MANIFEST.in
README.md
setup.py
dash_callback_chain/__init__.py
dash_callback_chain/bundle.js
dash_callback_chain/metadata.json
dash_callback_chain/version.py
dash_callback_chain.egg-info/PKG-INFO
dash_callback_chain.egg-info/SOURCES.txt
dash_callback_chain.egg-info/dependency_links.txt
dash_callback_chain.egg-info/top_level.txt