Metadata-Version: 1.0
Name: dash-callback-chain
Version: 0.0.2
Summary: Dash component to visualize callback chains
Home-page: UNKNOWN
Author: nicolaskruchten
Author-email: UNKNOWN
License: MIT
Platform: UNKNOWN
